nopapy/estimate/__init__.py
nopapy/estimate/estimate.py
nopapy/kernel/__init__.py
nopapy/kernel/custom.py
nopapy/kernel/kernel.py
nopapy/regression/__init__.py
nopapy/regression/regression.py
nopapy/utils/__init__.py
nopapy/utils/check.py
nopapy/utils/setting.py
npr/estimate/__init__.py
npr/estimate/estimate.py
npr/kernel/__init__.py
npr/kernel/custom.py
npr/kernel/kernel.py
npr/regression/__init__.py
npr/regression/regression.py
npr/utils/__init__.py
npr/utils/check.py
npr/utils/setting.py
npspy/estimate/__init__.py
npspy/estimate/estimate.py
npspy/kernel/__init__.py
npspy/kernel/custom.py
npspy/kernel/kernel.py
npspy/regression/__init__.py
npspy/regression/regression.py
npspy/utils/__init__.py
npspy/utils/check.py
npspy/utils/setting.py
npt/__init__.py
nopapy-1.0.2.dist-info/LICENSE.txt
nopapy-1.0.2.dist-info/METADATA
nopapy-1.0.2.dist-info/WHEEL
nopapy-1.0.2.dist-info/top_level.txt
nopapy-1.0.2.dist-info/RECORD
