Metadata-Version: 2.1
Name: nopapy
Version: 1.0.2
Summary: 「NopaPy」is an easy-to-use open-source library for non-parametric statistic.
Home-page: https://github.com/QVQZZZ/NopaPy
Author: Zhu Yaolin
Author-email: 540048506@qq.com
License: MIT
License-File: LICENSE.txt
